LindexURI/__init__.py
LindexURI-0.1.2.dist-info/LICENSE
LindexURI-0.1.2.dist-info/METADATA
LindexURI-0.1.2.dist-info/WHEEL
LindexURI-0.1.2.dist-info/top_level.txt
LindexURI-0.1.2.dist-info/RECORD
