Metadata-Version: 2.1
Name: LindexURI
Version: 0.1.2
Summary: Hadoop URI utility
Home-page: https://github.com/ozw1z5rd/LindexURI.git
Author: Alessio Palma
Author-email: ozw1z5rd@gmail.com
License: UNKNOWN
Platform: UNKNOWN
Classifier: Programming Language :: Python :: 2
Classifier: License :: OSI Approved :: MIT License
Classifier: Operating System :: OS Independent
